pyfreeflow/__init__.py
pyfreeflow/pipeline.py
pyfreeflow/registry.py
pyfreeflow/utils.py
pyfreeflow/ext/__init__.py
pyfreeflow/ext/buffer_operator.py
pyfreeflow/ext/crypto_operator.py
pyfreeflow/ext/data_transformer.py
pyfreeflow/ext/env_operator.py
pyfreeflow/ext/feed_requester.py
pyfreeflow/ext/file_operator.py
pyfreeflow/ext/html_requester.py
pyfreeflow/ext/jwt_operator.py
pyfreeflow/ext/mpd_executor.py
pyfreeflow/ext/pgsql_executor.py
pyfreeflow/ext/rest_api_requester.py
pyfreeflow/ext/sleep_operator.py
pyfreeflow/ext/sqlite_executor.py
pyfreeflow/ext/types.py
pyfreeflow-0.2.0.data/scripts/pyfreeflow-cli.py
pyfreeflow-0.2.0.dist-info/licenses/LICENSE
pyfreeflow-0.2.0.dist-info/METADATA
pyfreeflow-0.2.0.dist-info/WHEEL
pyfreeflow-0.2.0.dist-info/top_level.txt
pyfreeflow-0.2.0.dist-info/RECORD
