Metadata-Version: 2.4
Name: pyfreeflow
Version: 0.2.0
Summary: Async service toolchain
Home-page: https://github.com/senatoreg/pyfreeflow
Author: Giovanni Senatore
Author-email: 
License: AGPL-3.0-or-later
Classifier: Programming Language :: Python :: 3
Classifier: License :: OSI Approved :: GNU Affero General Public License v3 or later (AGPLv3+)
Classifier: Operating System :: OS Independent
Requires-Python: >=3.8
License-File: LICENSE
Requires-Dist: aiofiles>=24.1.0
Requires-Dist: aiohttp>=3.11.16
Requires-Dist: networkx>=3.2.1
Requires-Dist: pydot>=2.0.0
Requires-Dist: PyYAML>=5.4.1
Requires-Dist: tomli_w>=1.2.0
Requires-Dist: psycopg>=3.2.6
Requires-Dist: pyparsing>=3.1.2
Requires-Dist: PyJWT==2.10.1
Requires-Dist: lupa>=2.4
Requires-Dist: uvloop>=0.21.0
Requires-Dist: cryptography>=36.0.1
Requires-Dist: aiosqlite>=0.21.0
Requires-Dist: xxhash>=3.2.0
Requires-Dist: lxml>=6.0.2
Dynamic: author
Dynamic: classifier
Dynamic: description
Dynamic: description-content-type
Dynamic: home-page
Dynamic: license
Dynamic: license-file
Dynamic: requires-dist
Dynamic: requires-python
Dynamic: summary
